{
  "serial": "P-045",
  "img": {
    "ko": "images/ko/2024/Promo/P_045.webp"
  },
  "type": "cookie",
  "level": 1,
  "color": [
    "blue"
  ],
  "name": {
    "ko": "마카롱맛 쿠키",
    "zh-TW": "馬卡龍餅乾"
  },
  "hp": 3,
  "hasSkill": true,
  "skill": {
    "name": {
      "ko": "우당탕탕 행진",
      "zh-TW": "咚咚咚遊行"
    },
    "skillList": [
      {
        "condition": [
          "appear"
        ],
        "cost": {},
        "text": {
          "ko": "<자신의 패를 1장 덱의 아래로 되돌린다> 자신의 덱에서 1장까지 뽑는다.",
          "zh-TW": "<將1張自己的手牌放回牌庫最下方>從自己的牌庫抽最多1張牌。"
        },
        "effect": {
          "draw": 1
        }
      }
    ]
  },
  "attack": [
    {
      "cost": {
        "blue": 2
      },
      "text": {
        "ko": ""
      },
      "damage": 1,
      "name": {
        "ko": "박자를 맞춰요~",
        "zh-TW": "一起打節拍~"
      }
    }
  ],
  "hasFlip": false,
  "flip": {},
  "rarity": "P",
  "from": "프로모 카드 - 프로모션 팩 VOL.4",
  "releaseDate": "2024-10-01",
  "regulation": "A",
  "limit": 4,
  "qna": []
}